Metadata-Version: 1.2
Name: sentence-sem-sim
Version: 0.6
Summary: Sentence Semantic Similarity in Python.
Home-page: https://github.com/shaun-chiang/sentence_sem_sim/tree/master
Author: Shaun Chiang
Author-email: redbeansodapop@hotmail.com
License: MIT
Keywords: sentence,semantic,similarity
Platform: UNKNOWN
Requires-Python: >=3
